<?xml version="1.0" encoding="UTF-8"?>
<jcr:root xmlns:sling="http://sling.apache.org/jcr/sling/1.0" xmlns:cq="http://www.day.com/jcr/cq/1.0" xmlns:jcr="http://www.jcp.org/jcr/1.0" xmlns:mix="http://www.jcp.org/jcr/mix/1.0"
    jcr:primaryType="cq:Page">
    <jcr:content
        cq:cloudserviceconfigs="[[]]"
        cq:contextHubPath="/etc/cloudsettings/default/contexthub"
        cq:contextHubSegmentsPath="/etc/segmentation/contexthub"
        cq:designPath="/etc/designs/hertz"
        cq:lastModified="{Date}2017-09-07T14:49:20.142-04:00"
        cq:lastModifiedBy="admin"
        cq:lastReplicated="{Date}2017-09-19T03:01:48.891-04:00"
        cq:lastReplicatedBy="admin"
        cq:lastReplicationAction="Activate"
        cq:lastRolledout="{Date}2017-09-07T14:49:21.705-04:00"
        cq:lastRolledoutBy="admin"
        cq:template="/apps/hertz/templates/localeconfig"
        jcr:isCheckedOut="{Boolean}true"
        jcr:lastModified="{Date}2017-09-05T09:00:19.617-04:00"
        jcr:lastModifiedBy="admin"
        jcr:mixinTypes="[cq:LiveRelationship,cq:LiveSync,mix:versionable]"
        jcr:primaryType="cq:PageContent"
        jcr:title="fr-ca"
        jcr:uuid="3f04ef16-ab68-4e29-83ea-5e9657403d32"
        sling:resourceType="/apps/hertz/components/pages/localeconfig">
        <cq:LiveSyncConfig
            cq:excludedPaths="[termsconditions-config/us0/us/paylaterccr,termsconditions-config/us0/us/paynow,termsconditions-config/us0/us/paylaterus,termsconditions-config/us0/us/prepaid]"
            cq:isDeep="{Boolean}true"
            cq:master="/content/hertz-rac/data/en-us"
            cq:rolloutConfigs="[]"
            jcr:primaryType="cq:LiveCopy"/>
    </jcr:content>
    <importantinformation-config/>
    <termsconditions-config/>
    <ancillaries-display-configuration/>
    <ancillarycategory-config/>
    <rentalqualification-config/>
    <locations/>
    <errormessages-config/>
    <totalverbiage-config/>
    <country-config/>
    <creditcards/>
    <taxes-config/>
    <statelist/>
    <countrylist/>
    <taxConfig/>
    <airline-traincarrier/>
    <frequenttravelerprogram/>
</jcr:root>
